eoq3conceptsgen/__init__.py
eoq3conceptsgen/concepts.xlsx
eoq3conceptsgen/generatefromconcepts.py
eoq3conceptsgen/generatefromconceptscli.py
eoq3conceptsgen/pythontojson.py
eoq3conceptsgen/pythontojsoncli.py
eoq3conceptsgen/readconcepts.py
eoq3conceptsgen/sample.mako
eoq3conceptsgen-3.0.0.dist-info/licenses/LICENSE
eoq3conceptsgen-3.0.0.dist-info/METADATA
eoq3conceptsgen-3.0.0.dist-info/WHEEL
eoq3conceptsgen-3.0.0.dist-info/top_level.txt
eoq3conceptsgen-3.0.0.dist-info/RECORD
