Metadata-Version: 2.4
Name: eoq3conceptsgen
Version: 3.0.0
Summary: Scripts for generating code out of the formal definition of concepts using mako templates.
Author-email: Bjoern Annighoefer <bjoern.annighoefer@ils.uni-stuttgart.de>
Project-URL: Homepage, https://gitlab.com/eoq/py/eoq3conceptsgen
Project-URL: Issues, https://gitlab.com/eoq/py/eoq3conceptsgen/-/issues
Classifier: Programming Language :: Python :: 3
Classifier: License :: OSI Approved :: MIT License
Classifier: Operating System :: OS Independent
Requires-Python: >=3.10
License-File: LICENSE
Requires-Dist: pandas
Requires-Dist: mako
Requires-Dist: openpyxl
Dynamic: license-file
